dearbagplayer/__init__.py
dearbagplayer/__main__.py
dearbagplayer/config.py
dearbagplayer/data_pool_window.py
dearbagplayer/dearbagplayer.py
dearbagplayer/plot_window.py
dearbagplayer/rosbag_parser.py
dearbagplayer/timeline.py
dearbagplayer/timeline_widgets.py
DearBagPlayer-0.3.0.dist-info/LICENSE
DearBagPlayer-0.3.0.dist-info/METADATA
DearBagPlayer-0.3.0.dist-info/WHEEL
DearBagPlayer-0.3.0.dist-info/entry_points.txt
DearBagPlayer-0.3.0.dist-info/top_level.txt
DearBagPlayer-0.3.0.dist-info/RECORD
