Metadata-Version: 2.1
Name: DearBagPlayer
Version: 0.3.0
Summary: DearBagPlayer is a flexible rosbag player based on Dear PyGui in Python.
Author-email: Wei Wang <wei.wang.bit@outlook.com>
License: MIT
Project-URL: Homepage, https://github.com/Magic-wei/DearBagPlayer
Project-URL: Bug Tracker, https://github.com/Magic-wei/DearBagPlayer/issues
Keywords: DearPyGui,Visualization,rosbag
Classifier: Programming Language :: Python :: 3
Classifier: License :: OSI Approved :: MIT License
Classifier: Operating System :: OS Independent
Requires-Python: >=3.9
License-File: LICENSE
Requires-Dist: dearpygui >=1.11.1
Requires-Dist: numpy >=2.0.1
Requires-Dist: rosbag >=1.15.11
